abstract_response_generator/__init__.py
abstract_response_generator/client_side/__init__.py
abstract_response_generator/client_side/response_generator_client.py
abstract_response_generator/client_side/response_generator_local_module.py
abstract_response_generator/server_side/__init__.py
abstract_response_generator/server_side/abstract_rg_apl_builder.py
abstract_response_generator/server_side/abstract_rg_controller.py
abstract_response_generator/server_side/abstract_rg_update_state.py
abstract_response_generator/server_side/app.py
twiz_response_generators_TWIZ_TEAM-0.0.8.dist-info/METADATA
twiz_response_generators_TWIZ_TEAM-0.0.8.dist-info/WHEEL
twiz_response_generators_TWIZ_TEAM-0.0.8.dist-info/top_level.txt
twiz_response_generators_TWIZ_TEAM-0.0.8.dist-info/RECORD
