Metadata-Version: 2.1
Name: twiz-response-generators-TWIZ-TEAM
Version: 0.0.8
Summary: Abstract response generator classes to be user in alexa taskbot development. Requires cobot access.
Home-page: https://github.com/pypa/sampleproject
Author: TWIZ-TEAM
Author-email: alexa-twiz@googlegroups.com
Project-URL: Bug Tracker, https://github.com/pypa/sampleproject/issues
Classifier: Programming Language :: Python :: 3
Classifier: License :: OSI Approved :: MIT License
Classifier: Operating System :: OS Independent
Requires-Python: >=3.6
